.coveragerc
.mailmap
.testr.conf
AUTHORS
CONTRIBUTING.rst
ChangeLog
HACKING.rst
LICENSE
MANIFEST.in
README.rst
babel.cfg
requirements.txt
setup.cfg
setup.py
test-requirements.txt
tox.ini
demo/README.rst
demo/ansible.cfg
demo/hosts
demo/requirements.txt
demo/tiny-resources.yml
demo/tiny.yml
demo/export/.placeholder
doc/source/background.rst
doc/source/conf.py
doc/source/contributing.rst
doc/source/glossary.rst
doc/source/history.rst
doc/source/index.rst
doc/source/installation.rst
doc/source/resource_file.rst
doc/source/usage.rst
downpour/__init__.py
downpour/app.py
downpour/download.py
downpour/export.py
downpour/query.py
downpour/resolver.py
downpour/resources.py
downpour/tests/__init__.py
downpour/tests/base.py
downpour/tests/test_aerostat.py
os_downpour.egg-info/PKG-INFO
os_downpour.egg-info/SOURCES.txt
os_downpour.egg-info/dependency_links.txt
os_downpour.egg-info/entry_points.txt
os_downpour.egg-info/not-zip-safe
os_downpour.egg-info/pbr.json
os_downpour.egg-info/requires.txt
os_downpour.egg-info/top_level.txt
releasenotes/notes/.placeholder
releasenotes/source/conf.py
releasenotes/source/index.rst
releasenotes/source/unreleased.rst
releasenotes/source/_static/.placeholder
releasenotes/source/_templates/.placeholder